pyws66i/__init__.py
pyws66i-1.0.dist-info/LICENSE.txt
pyws66i-1.0.dist-info/METADATA
pyws66i-1.0.dist-info/WHEEL
pyws66i-1.0.dist-info/top_level.txt
pyws66i-1.0.dist-info/zip-safe
pyws66i-1.0.dist-info/RECORD
