Metadata-Version: 2.1
Name: pyws66i
Version: 1.0
Summary: Python API for talking to Soundavo's WS66i 6-zone amplifier using the telnet protocol
Home-page: https://github.com/ssaenger/pyws66i
Download-URL: https://github.com/ssaenger/pyws66i/archive/v1.0.tar.gz
Author: Shawn Saenger
Author-email: shawnsaenger@gmail.com
License: MIT
Platform: UNKNOWN
Classifier: Development Status :: 5 - Production/Stable
Classifier: Programming Language :: Python :: 3.8
Classifier: Programming Language :: Python :: 3.9
Classifier: License :: OSI Approved :: MIT License
License-File: LICENSE.txt
